pattern_matching/__init__.py
pattern_matching/core/__init__.py
pattern_matching/core/match.py
pattern_matching/core/pattern.py
pattern_matching-1.0.1.dist-info/METADATA
pattern_matching-1.0.1.dist-info/RECORD
pattern_matching-1.0.1.dist-info/WHEEL
pattern_matching-1.0.1.dist-info/top_level.txt
