Metadata-Version: 2.1
Name: pattern-matching
Version: 1.0.1
Summary: effective and graceful pattern matching for original python
Home-page: https://github.com/Xython/pattern-matching
Author: thautwarm
Author-email: twshere@outlook.com
License: MIT
Platform: any
Classifier: Programming Language :: Python :: 3.6
Classifier: Programming Language :: Python :: 3.7
Classifier: Programming Language :: Python :: Implementation :: CPython
